tost-0.1.2.dist-info/METADATA
tost-0.1.2.dist-info/WHEEL
tost/__init__.py
tost/_tost.pyd
tost/tost.py
tost-0.1.2.dist-info/RECORD
