Metadata-Version: 2.4
Name: tost
Version: 0.1.2
Classifier: Development Status :: 4 - Beta
Classifier: Intended Audience :: Developers
Classifier: License :: OSI Approved :: MIT License
Classifier: Programming Language :: Rust
Classifier: Programming Language :: Python :: 3
Classifier: Programming Language :: Python :: 3.8
Classifier: Programming Language :: Python :: 3.9
Classifier: Programming Language :: Python :: 3.10
Classifier: Programming Language :: Python :: 3.11
Classifier: Programming Language :: Python :: 3.12
Classifier: Programming Language :: Python :: Implementation :: CPython
Classifier: Programming Language :: Python :: Implementation :: PyPy
Classifier: Topic :: Software Development :: Libraries :: Python Modules
Classifier: Topic :: Text Processing :: Markup
Summary: TOON (Token-Oriented Object Notation) Python API - A compact data format optimized for LLM token usage
Keywords: toon,token,format,llm,serialization,encoding,decoding
Author-email: JohanLi233 <li_zhonghan@qq.com>
License: MIT
Requires-Python: >=3.8
Project-URL: Homepage, https://github.com/JohanLi233/tost
Project-URL: Repository, https://github.com/JohanLi233/tost
Project-URL: Documentation, https://github.com/JohanLi233/tost#readme
Project-URL: Issues, https://github.com/JohanLi233/tost/issues
